llmmaster/__init__.py
llmmaster/anthropic_models.py
llmmaster/cerebras_models.py
llmmaster/config.py
llmmaster/deepseek_models.py
llmmaster/elevenlabs_models.py
llmmaster/flux1_fal_models.py
llmmaster/google_models.py
llmmaster/groq_models.py
llmmaster/inceptionlabs_models.py
llmmaster/llmbase.py
llmmaster/llmmaster.py
llmmaster/lumaai_models.py
llmmaster/meshy_models.py
llmmaster/mistral_models.py
llmmaster/multipart_formdata_model.py
llmmaster/openai_models.py
llmmaster/perplexity_models.py
llmmaster/replica_models.py
llmmaster/root_model.py
llmmaster/runway_models.py
llmmaster/sambanova_models.py
llmmaster/skybox_models.py
llmmaster/stable_diffusion_models.py
llmmaster/tripo_models.py
llmmaster/utils.py
llmmaster/voicevox_models.py
llmmaster/xai_models.py
llmmaster-1.4.6.dist-info/licenses/LICENSE
llmmaster-1.4.6.dist-info/METADATA
llmmaster-1.4.6.dist-info/WHEEL
llmmaster-1.4.6.dist-info/top_level.txt
llmmaster-1.4.6.dist-info/RECORD
