Metadata-Version: 2.4
Name: llmmaster
Version: 1.4.6
Summary: A unified interface for interacting with multiple LLMs and generative AIs.
Author-email: Daisuke Yamaguchi <daicom0204@gmail.com>
Project-URL: Homepage, https://habatakurikei.com/
Project-URL: GitHub, https://github.com/Habatakurikei/llmmaster
Project-URL: PyPI, https://pypi.org/project/llmmaster/
Classifier: Development Status :: 3 - Alpha
Classifier: Intended Audience :: Developers
Classifier: License :: OSI Approved :: MIT License
Classifier: Operating System :: OS Independent
Classifier: Programming Language :: Python :: 3
Classifier: Programming Language :: Python :: 3.10
Classifier: Programming Language :: Python :: 3.11
Classifier: Programming Language :: Python :: 3.12
Requires-Python: >=3.10
License-File: LICENSE
Requires-Dist: requests>=2.32.3
Requires-Dist: requests-toolbelt>=1.0.0
Provides-Extra: dev
Requires-Dist: pytest>=8.3.4; extra == "dev"
Requires-Dist: flake8>=7.1.1; extra == "dev"
Requires-Dist: build>=1.2.2.post1; extra == "dev"
Requires-Dist: twine>=6.1.0; extra == "dev"
Dynamic: license-file
